code_beatrix/__init__.py
code_beatrix/rss_blog_list.xml
code_beatrix/ai/__init__.py
code_beatrix/ai/dlbase.py
code_beatrix/ai/image_segmentation.py
code_beatrix/algorithm/__init__.py
code_beatrix/algorithm/classroom.py
code_beatrix/algorithm/tsp.py
code_beatrix/algorithm/data/__init__.py
code_beatrix/algorithm/data/prenoms_w.txt
code_beatrix/art/__init__.py
code_beatrix/art/moviepy_context.py
code_beatrix/art/video.py
code_beatrix/art/video_drawing.py
code_beatrix/art/videodl.py
code_beatrix/art/data/__init__.py
code_beatrix/automation/__init__.py
code_beatrix/automation/notebook_const_helper.py
code_beatrix/automation/notebook_test_helper.py
code_beatrix/faq/__init__.py
code_beatrix/faq/faq_python.py
code_beatrix/ipythonhelper/__init__.py
code_beatrix/ipythonhelper/magic_scratch.py
code_beatrix/ipythonhelper/nbcanvas.py
code_beatrix/ipythonhelper/path_helper.py
code_beatrix/jsscripts/__init__.py
code_beatrix/jsscripts/nbsnap.py
code_beatrix/jsscripts/Snapin8r2/README.md
code_beatrix/jsscripts/Snapin8r2/__init__.py
code_beatrix/jsscripts/Snapin8r2/snapin8r2.js
code_beatrix/jsscripts/snap/CONTRIBUTING.md
code_beatrix/jsscripts/snap/FileSaver.min.js
code_beatrix/jsscripts/snap/README.md
code_beatrix/jsscripts/snap/Snap! Connectivity Strategy.pdf
code_beatrix/jsscripts/snap/__init__.py
code_beatrix/jsscripts/snap/blocks.js
code_beatrix/jsscripts/snap/byob.js
code_beatrix/jsscripts/snap/click.wav
code_beatrix/jsscripts/snap/cloud.js
code_beatrix/jsscripts/snap/favicon.ico
code_beatrix/jsscripts/snap/gui.js
code_beatrix/jsscripts/snap/history.txt
code_beatrix/jsscripts/snap/index.html
code_beatrix/jsscripts/snap/lang-ar.js
code_beatrix/jsscripts/snap/lang-bg.js
code_beatrix/jsscripts/snap/lang-bn.js
code_beatrix/jsscripts/snap/lang-ca.js
code_beatrix/jsscripts/snap/lang-cs.js
code_beatrix/jsscripts/snap/lang-de.js
code_beatrix/jsscripts/snap/lang-dk.js
code_beatrix/jsscripts/snap/lang-el.js
code_beatrix/jsscripts/snap/lang-eo.js
code_beatrix/jsscripts/snap/lang-es.js
code_beatrix-0.6.685.dist-info/LICENSE.txt
code_beatrix-0.6.685.dist-info/METADATA
code_beatrix-0.6.685.dist-info/WHEEL
code_beatrix-0.6.685.dist-info/top_level.txt
code_beatrix-0.6.685.dist-info/RECORD
