Metadata-Version: 2.1
Name: code-beatrix
Version: 0.6.685
Summary: Exercices pour apprendre la programmation, les algorithmes, et faire des coding goûters.
Home-page: http://lesenfantscodaient.fr/
Author: Xavier Dupré
Author-email: xavier.dupre@gmail.com
License: MIT
Download-URL: https://github.com/sdpython/code_beatrix/
Keywords: code_beatrix,coding goûter
Platform: UNKNOWN
Classifier: Programming Language :: Python :: 3
Classifier: Intended Audience :: Developers
Classifier: Topic :: Scientific/Engineering
Classifier: Topic :: Education
Classifier: License :: OSI Approved :: MIT License
Classifier: Development Status :: 5 - Production/Stable
Requires-Dist: pyquickhelper (>=1.9)
Provides-Extra: art
Requires-Dist: pytube3 ; extra == 'art'
Requires-Dist: moviepy (==1.0.0) ; extra == 'art'
Provides-Extra: faq
Requires-Dist: pytube3 ; extra == 'faq'
